Workbook

Sheet Summary
A1: SaaS Unit Economics — Summary
A2: Generated by Madav · figures recompute live in Excel
B4: =Projection!M7 -> 285.15218 | E4: =Projection!M9 -> 22812.174
B6: ENDING CUSTOMERS (M12) | E6: MRR (M12)
B8: =Projection!M9*12 -> 273746.09 | E8: =Projection!M14 -> 1.2655853
B10: ARR | E10: LTV : CAC

Sheet Assumptions
A1: SaaS Unit Economics — Assumptions
A3: STARTING POSITION
A4: Starting customers | B4: 200 | C4: Month-1 active customers
A5: ARPU ($/mo) | B5: 80 | C5: Avg revenue per user / month
A7: GROWTH & RETENTION
A8: MoM customer growth | B8: 0.06 | C8: New logos as % of base
A9: Monthly churn | B9: 0.03 | C9: Logo churn / month
A11: ECONOMICS
A12: Gross margin | B12: 0.8 | C12: Contribution margin
A13: S&M spend / mo ($) | B13: 28000 | C13: Sales & marketing / month
A14: Discount rate (annual) | B14: 0.12 | C14: For DCF-style LTV
A16: DERIVED METRICS
A17: Avg customer lifetime (mo) | B17: =1/Assumptions!$B$9 -> 33.333333 | C17: 1 / monthly churn
A18: Simple LTV ($) | B18: =(Assumptions!$B$5*Assumptions!$B$12)/Assumptions!$B$9 -> 2133.3333 | C18: ARPU x margin / churn

Sheet Projection
A1: 12-Month Projection
A3: Metric | B3: M1 | C3: M2 | D3: M3 | E3: M4 | F3: M5 | G3: M6 | H3: M7 | I3: M8 | J3: M9 | K3: M10 | L3: M11 | M3: M12
A4: Beginning customers | B4: =Assumptions!$B$4 -> 200 | C4: =B7 -> 206 | D4: =C7 -> 212.18 | E4: =D7 -> 218.5454 | F4: =E7 -> 225.10176 | G4: =F7 -> 231.85481 | H4: =G7 -> 238.81046 | I4: =H7 -> 245.97477 | J4: =I7 -> 253.35402 | ... M4: =L7 -> 276.84677
A5: New customers | B5: =B4*Assumptions!$B$8 -> 12 | C5: =C4*Assumptions!$B$8 -> 12.36 | D5: =D4*Assumptions!$B$8 -> 12.7308 | E5: =E4*Assumptions!$B$8 -> 13.112724 | F5: =F4*Assumptions!$B$8 -> 13.506106 | G5: =G4*Assumptions!$B$8 -> 13.911289 | H5: =H4*Assumptions!$B$8 -> 14.328628 | I5: =I4*Assumptions!$B$8 -> 14.758486 | ... M5: =M4*Assumptions!$B$8 -> 16.610806
A6: Churned customers | B6: =B4*Assumptions!$B$9 -> 6 | C6: =C4*Assumptions!$B$9 -> 6.18 | D6: =D4*Assumptions!$B$9 -> 6.3654 | E6: =E4*Assumptions!$B$9 -> 6.556362 | F6: =F4*Assumptions!$B$9 -> 6.7530529 | G6: =G4*Assumptions!$B$9 -> 6.9556444 | H6: =H4*Assumptions!$B$9 -> 7.1643138 | I6: =I4*Assumptions!$B$9 -> 7.3792432 | ... M6: =M4*Assumptions!$B$9 -> 8.3054032
A7: Ending customers | B7: =B4+B5-B6 -> 206 | C7: =C4+C5-C6 -> 212.18 | D7: =D4+D5-D6 -> 218.5454 | E7: =E4+E5-E6 -> 225.10176 | F7: =F4+F5-F6 -> 231.85481 | G7: =G4+G5-G6 -> 238.81046 | H7: =H4+H5-H6 -> 245.97477 | I7: =I4+I5-I6 -> 253.35402 | ... M7: =M4+M5-M6 -> 285.15218
A8: ARPU ($/mo) | B8: =Assumptions!$B$5 -> 80 | C8: =Assumptions!$B$5 -> 80 | D8: =Assumptions!$B$5 -> 80 | E8: =Assumptions!$B$5 -> 80 | F8: =Assumptions!$B$5 -> 80 | G8: =Assumptions!$B$5 -> 80 | H8: =Assumptions!$B$5 -> 80 | I8: =Assumptions!$B$5 -> 80 | ... M8: =Assumptions!$B$5 -> 80
A9: MRR ($) | B9: =B7*B8 -> 16480 | C9: =C7*C8 -> 16974.4 | D9: =D7*D8 -> 17483.632 | E9: =E7*E8 -> 18008.141 | F9: =F7*F8 -> 18548.385 | G9: =G7*G8 -> 19104.837 | H9: =H7*H8 -> 19677.982 | I9: =I7*I8 -> 20268.321 | ... M9: =M7*M8 -> 22812.174
A10: Gross profit ($) | B10: =B9*Assumptions!$B$12 -> 13184 | C10: =C9*Assumptions!$B$12 -> 13579.52 | D10: =D9*Assumptions!$B$12 -> 13986.906 | E10: =E9*Assumptions!$B$12 -> 14406.513 | F10: =F9*Assumptions!$B$12 -> 14838.708 | G10: =G9*Assumptions!$B$12 -> 15283.869 | H10: =H9*Assumptions!$B$12 -> 15742.385 | I10: =I9*Assumptions!$B$12 -> 16214.657 | ... M10: =M9*Assumptions!$B$12 -> 18249.739
A11: S&M spend ($) | B11: =Assumptions!$B$13 -> 28000 | C11: =Assumptions!$B$13 -> 28000 | D11: =Assumptions!$B$13 -> 28000 | E11: =Assumptions!$B$13 -> 28000 | F11: =Assumptions!$B$13 -> 28000 | G11: =Assumptions!$B$13 -> 28000 | H11: =Assumptions!$B$13 -> 28000 | I11: =Assumptions!$B$13 -> 28000 | ... M11: =Assumptions!$B$13 -> 28000
A12: CAC ($) | B12: =B11/B5 -> 2333.3333 | C12: =C11/C5 -> 2265.3722 | D12: =D11/D5 -> 2199.3905 | E12: =E11/E5 -> 2135.3305 | F12: =F11/F5 -> 2073.1364 | G12: =G11/G5 -> 2012.7538 | H12: =H11/H5 -> 1954.1299 | I12: =I11/I5 -> 1897.2135 | ... M12: =M11/M5 -> 1685.6496
A13: LTV ($) | B13: =B8*Assumptions!$B$12/Assumptions!$B$9 -> 2133.3333 | C13: =C8*Assumptions!$B$12/Assumptions!$B$9 -> 2133.3333 | D13: =D8*Assumptions!$B$12/Assumptions!$B$9 -> 2133.3333 | E13: =E8*Assumptions!$B$12/Assumptions!$B$9 -> 2133.3333 | F13: =F8*Assumptions!$B$12/Assumptions!$B$9 -> 2133.3333 | G13: =G8*Assumptions!$B$12/Assumptions!$B$9 -> 2133.3333 | H13: =H8*Assumptions!$B$12/Assumptions!$B$9 -> 2133.3333 | I13: =I8*Assumptions!$B$12/Assumptions!$B$9 -> 2133.3333 | ... M13: =M8*Assumptions!$B$12/Assumptions!$B$9 -> 2133.3333
A14: LTV : CAC | B14: =B13/B12 -> 0.91428571 | C14: =C13/C12 -> 0.94171429 | D14: =D13/D12 -> 0.96996571 | E14: =E13/E12 -> 0.99906469 | F14: =F13/F12 -> 1.0290366 | G14: =G13/G12 -> 1.0599077 | H14: =H13/H12 -> 1.091705 | I14: =I13/I12 -> 1.1244561 | ... M14: =M13/M12 -> 1.2655853
A15: CAC payback (mo) | B15: =B12/(B8*Assumptions!$B$12) -> 36.458333 | C15: =C12/(C8*Assumptions!$B$12) -> 35.39644 | D15: =D12/(D8*Assumptions!$B$12) -> 34.365476 | E15: =E12/(E8*Assumptions!$B$12) -> 33.36454 | F15: =F12/(F8*Assumptions!$B$12) -> 32.392757 | G15: =G12/(G8*Assumptions!$B$12) -> 31.449279 | H15: =H12/(H8*Assumptions!$B$12) -> 30.53328 | I15: =I12/(I8*Assumptions!$B$12) -> 29.643961 | ... M15: =M12/(M8*Assumptions!$B$12) -> 26.338276

Sheet Analysis
A1: Quarterly Analysis — pivot summary
A3: Quarter | B3: New custs | C3: Churned | D3: Ending | E3: MRR ($) | F3: Gross profit ($) | G3: S&M ($)
A4: Q1 | B4: =SUM(Projection!B5:D5) -> 37.0908 | C4: =SUM(Projection!B6:D6) -> 18.5454 | D4: =Projection!D7 -> 218.5454 | E4: =SUM(Projection!B9:D9) -> 50938.032 | F4: =SUM(Projection!B10:D10) -> 40750.426 | G4: =SUM(Projection!B11:D11) -> 84000
A5: Q2 | B5: =SUM(Projection!E5:G5) -> 40.530119 | C5: =SUM(Projection!E6:G6) -> 20.265059 | D5: =Projection!G7 -> 238.81046 | E5: =SUM(Projection!E9:G9) -> 55661.363 | F5: =SUM(Projection!E10:G10) -> 44529.09 | G5: =SUM(Projection!E11:G11) -> 84000
A6: Q3 | B6: =SUM(Projection!H5:J5) -> 44.288355 | C6: =SUM(Projection!H6:J6) -> 22.144177 | D6: =Projection!J7 -> 260.95464 | E6: =SUM(Projection!H9:J9) -> 60822.674 | F6: =SUM(Projection!H10:J10) -> 48658.139 | G6: =SUM(Projection!H11:J11) -> 84000
A7: Q4 | B7: =SUM(Projection!K5:M5) -> 48.395081 | C7: =SUM(Projection!K6:M6) -> 24.197541 | D7: =Projection!M7 -> 285.15218 | E7: =SUM(Projection!K9:M9) -> 66462.578 | F7: =SUM(Projection!K10:M10) -> 53170.063 | G7: =SUM(Projection!K11:M11) -> 84000
